README.md
setup.py
pcqq/__init__.py
pcqq/bot.py
pcqq/client.py
pcqq/handle.py
pcqq/logger.py
pcqq/message.py
pcqq/plugin.py
pcqq/session.py
pcqq/binary/__init__.py
pcqq/binary/qqtea.py
pcqq/binary/qqtlv.py
pcqq/binary/reader.py
pcqq/binary/writer.py
pcqq/const/__init__.py
pcqq/const/ctx.py
pcqq/const/packet.py
pcqq/const/typing.py
pcqq/network/__init__.py
pcqq/network/pcapi.py
pcqq/network/webapi.py
pcqq/network/wtlogin.py
pcqq/utils/__init__.py
pcqq/utils/group.py
pcqq/utils/helper.py
pcqq/utils/imsize.py
pcqq/utils/qrcode.py
pcqq/utils/sqlite.py
py_pcqq.egg-info/PKG-INFO
py_pcqq.egg-info/SOURCES.txt
py_pcqq.egg-info/dependency_links.txt
py_pcqq.egg-info/top_level.txt