Metadata-Version: 1.0
Name: py-pcqq
Version: 1.3.0
Summary: 一个使用pcqq协议的简易python qqbot库
Home-page: https://github.com/DawnNights/py-pcqq
Author: DawnNights
Author-email: 2224825532@qq.com
License: UNKNOWN
Platform: UNKNOWN
